{
    "students": [
        {
            "firstname": "jim",
            "lastname": "foley",
            "id": 12695421,
            "avatar": "/img/avatar.svg"
        },
        {
            "firstname": "phyllis",
            "lastname": "mcgowan",
            "id": 12879452,
            "avatar": "/img/avatar.svg"
        },
        {
            "firstname": "bernadette",
            "lastname": "ponich",
            "id": 128794522,
            "avatar": "/img/avatar.svg"
        },
        {
            "firstname": "grant",
            "lastname": "hammond",
            "id": 254129,
            "avatar": "/img/avatar.svg" 
        },
        {
            "firstname": "grant",
            "lastname": "shu",
            "id": 4578156,
            "avatar": "/img/avatar.svg" 
        },
        {
            "firstname": "nancy",
            "lastname": "ozibko",
            "id": 45814632,
            "avatar": "/img/avatar.svg" 
        },
        {
            "firstname": "adelt",
            "lastname": "boshnil",
            "id": 48521515,
            "avatar": "/img/avatar.svg" 
        },
        {
            "firstname": "kasande",
            "lastname": "deminklo",
            "id": 7514698,
            "avatar": "/img/avatar.svg" 
        },
        {
            "firstname": "mirimian",
            "lastname": "yamishklio",
            "id": 61973258,
            "avatar": "/img/avatar.svg" 
        }, 
        {
            "firstname": "nirmia",
            "lastname": "mac millan",
            "id": 19375421,
            "avatar": "/img/avatar.svg" 
        },
        {
            "firstname": "jack",
            "lastname": "elbhert",
            "id": 2388749,
            "avatar": "/img/avatar.svg" 
        },
        {
            "firstname": "emil",
            "lastname": "heskie",
            "id": 1758654,
            "avatar": "/img/avatar.svg" 
        },
        {
            "firstname": "ombama",
            "lastname": "klimtom",
            "id": 9651287,
            "avatar": "/img/avatar.svg" 
        },
        {
            "firstname": "kumira",
            "lastname": "sukmira",
            "id": 5422589,
            "avatar": "/img/avatar.svg" 
        },
        {
            "firstname": "bindar",
            "lastname": "ganganmehr",
            "id": 3257441,
            "avatar": "/img/avatar.svg" 
        }
        
    ]
}